DummyPygreet/__init__.py
DummyPygreet/location.py
dummypygreet-0.1.0.dist-info/WHEEL
dummypygreet-0.1.0.dist-info/METADATA
dummypygreet-0.1.0.dist-info/RECORD
