Metadata-Version: 2.1
Name: dummypygreet
Version: 0.1.0
Summary: 
Author: Suresh Babu Jonathan
Author-email: Jonathan.SureshBabu-EE@infineon.com
Requires-Python: >=3.7,<4.0
Classifier: Programming Language :: Python :: 3
Classifier: Programming Language :: Python :: 3.7
Classifier: Programming Language :: Python :: 3.8
Classifier: Programming Language :: Python :: 3.9
Requires-Dist: arrow (>=0.17.0,<0.18.0)
Requires-Dist: requests (>=2.25.0,<3.0.0)
